enumcricketlib/__init__.py
enumcricketlib/searchswitch.py
enumcricketlib/serialswitch.py
enumcricketlib/switch.py
enumcricketlib/switch2101.py
enumcricketlib/switch2301.py
enumcricketlib/switch3141.py
enumcricketlib/switch3142.py
enumcricketlib/switch3201.py
enumcricketlib/usbswitch.py
enumcricketapi-1.0.8.dist-info/LICENSE
enumcricketapi-1.0.8.dist-info/METADATA
enumcricketapi-1.0.8.dist-info/WHEEL
enumcricketapi-1.0.8.dist-info/top_level.txt
enumcricketapi-1.0.8.dist-info/RECORD
