Metadata-Version: 2.1
Name: enumcricketapi
Version: 1.0.8
Summary: API for MCCI Connection exercisers
Home-page: UNKNOWN
Author: MCCI Corporation
Author-email: UNKNOWN
License: UNKNOWN
Platform: UNKNOWN
